napari_unet/__init__.py
napari_unet/architecture.py
napari_unet/cldice_loss.py
napari_unet/compare_metrics.py
napari_unet/data_augment.py
napari_unet/data_control.py
napari_unet/datasets.py
napari_unet/losses.py
napari_unet/metrics.py
napari_unet/napari.yaml
napari_unet/plotting.py
napari_unet/qt_workers.py
napari_unet/result_tables.py
napari_unet/skeleton_measures.py
napari_unet/soft_skeleton.py
napari_unet/unet_inference.py
napari_unet/unet_training.py
napari_unet/dev/test_soft_skel.py
napari_unet/dev/test_unet.py
napari_unet/tiles/__init__.py
napari_unet/tiles/patch.py
napari_unet/tiles/plot.py
napari_unet/tiles/recalibrate.py
napari_unet/tiles/tiler.py
napari_unet/widgets/compare_results_widget.py
napari_unet/widgets/skeleton_measures_widget.py
napari_unet/widgets/tiling_widget.py
napari_unet/widgets/unet_inference_widget.py
napari_unet/widgets/unet_training_widget.py
napari_unet-1.0.0.dist-info/licenses/LICENSE
napari_unet-1.0.0.dist-info/METADATA
napari_unet-1.0.0.dist-info/WHEEL
napari_unet-1.0.0.dist-info/entry_points.txt
napari_unet-1.0.0.dist-info/top_level.txt
napari_unet-1.0.0.dist-info/RECORD
