Metadata-Version: 2.4
Name: napari-unet
Version: 1.0.0
Summary: A Napari plugin allowing to train and run inference of a UNet model.
Author: Clément H. BENEDETTI
Author-email: clement.benedetti@mri.cnrs.fr
License: MIT License
Project-URL: Bug Tracker, https://github.com/MontpellierRessourcesImagerie/napari-unet/issues
Project-URL: Documentation, https://github.com/MontpellierRessourcesImagerie/napari-unet#README.md
Project-URL: Source Code, https://github.com/MontpellierRessourcesImagerie/napari-unet
Project-URL: User Support, https://github.com/MontpellierRessourcesImagerie/napari-unet/issues
Classifier: Development Status :: 2 - Pre-Alpha
Classifier: Framework :: napari
Classifier: Intended Audience :: Developers
Classifier: License :: OSI Approved :: MIT License
Classifier: Operating System :: OS Independent
Classifier: Programming Language :: Python
Classifier: Programming Language :: Python :: 3
Classifier: Programming Language :: Python :: 3 :: Only
Classifier: Programming Language :: Python :: 3.9
Classifier: Programming Language :: Python :: 3.10
Classifier: Programming Language :: Python :: 3.11
Classifier: Programming Language :: Python :: 3.12
Classifier: Topic :: Scientific/Engineering :: Image Processing
Requires-Python: >=3.10
License-File: LICENSE
Requires-Dist: numpy
Requires-Dist: scikit-image
Requires-Dist: scikit-learn
Requires-Dist: scipy
Requires-Dist: pint
Requires-Dist: tifffile
Requires-Dist: tensorflow==2.19
Requires-Dist: skan
Requires-Dist: matplotlib
Requires-Dist: opencv-python-headless
Provides-Extra: testing
Requires-Dist: tox; extra == "testing"
Requires-Dist: pytest; extra == "testing"
Requires-Dist: pytest-cov; extra == "testing"
Requires-Dist: pytest-qt; extra == "testing"
Requires-Dist: pyqt5; extra == "testing"
Requires-Dist: numpy; extra == "testing"
Requires-Dist: qtpy; extra == "testing"
Requires-Dist: sphinx_rtd_theme; extra == "testing"
Requires-Dist: myst_parser; extra == "testing"
Requires-Dist: sphinx_tabs; extra == "testing"
Provides-Extra: and-napari
Requires-Dist: napari[all]; extra == "and-napari"
Dynamic: license-file
